{
  "parent": "minecraft:block/cube",
  "textures": {
    "side": "notitlemod:block/machine_side",
    "front": "notitlemod:block/crusher_front",
    "top": "notitlemod:block/machine_top"
  },

  "elements": [
    {
      "from": [0,0,0],
      "to": [16,16,16],
      "faces": {
        "north": {
          "texture": "#front"
        },
        "south": {
          "texture": "#side"
        },
        "east": {
          "texture": "#side"
        },
        "west": {
          "texture": "#side"
        },
        "up": {
          "texture": "#top"
        },
        "down": {
          "texture": "#side"
        }
      }
    }
  ]
}